{
    "name": "Address",
    "fields": [
        {
            "fieldName": "address1",
            "fieldType": "String",
            "fieldValidateRules": [
                "required"
            ]
        },
        {
            "fieldName": "address2",
            "fieldType": "String"
        },
        {
            "fieldName": "city",
            "fieldType": "String",
            "fieldValidateRules": [
                "required"
            ]
        },
        {
            "fieldName": "postcode",
            "fieldType": "String",
            "fieldValidateRules": [
                "required",
                "maxlength"
            ],
            "fieldValidateRulesMaxlength": 6
        },
        {
            "fieldName": "country",
            "fieldType": "String",
            "fieldValidateRules": [
                "required",
                "maxlength"
            ],
            "fieldValidateRulesMaxlength": 20
        }
    ],
    "relationships": [
        {
            "relationshipType": "many-to-one",
            "relationshipName": "user",
            "otherEntityName": "user",
            "otherEntityField": "login"
        }
    ],
    "changelogDate": "20190122231138",
    "entityTableName": "address",
    "dto": "no",
    "pagination": "pager",
    "service": "no",
    "jpaMetamodelFiltering": false,
    "fluentMethods": true,
    "clientRootFolder": "",
    "applications": "*"
}